traincif/__init__.py
traincif-0.2.0.dist-info/METADATA
traincif-0.2.0.dist-info/WHEEL
traincif-0.2.0.dist-info/licenses/LICENSE-MIT.txt
traincif-0.2.0.dist-info/licenses/LICENSE-WTFPL.txt
traincif-0.2.0.dist-info/RECORD
