Metadata-Version: 2.4
Name: traincif
Version: 0.2.0
Summary: Parse Common Interchange Format (CIF) files commonly used when working with UK train data
Project-URL: Documentation, https://github.com/iamawatermelo/traincif#readme
Project-URL: Issues, https://github.com/iamawatermelo/traincif/issues
Project-URL: Source, https://github.com/iamawatermelo/traincif
License-Expression: MIT
License-File: LICENSE-MIT.txt
License-File: LICENSE-WTFPL.txt
Requires-Python: >=3.13
